datalake/__init__.py
datalake/_version.py
datalake/archive.py
datalake/config_helpers.py
datalake/crtime.py
datalake/dlfile.py
datalake/logging_helpers.py
datalake/queue.py
datalake/translator.py
datalake/common/__init__.py
datalake/common/conf.py
datalake/common/errors.py
datalake/common/metadata.py
datalake/common/record.py
datalake/scripts/__init__.py
datalake/scripts/cli.py
datalake/tests/__init__.py
datalake/tests/conftest.py
datalake/tests/test_conf.py
datalake/tests/test_metadata.py
datalake/tests/test_record.py
datalake-2.5.8.dist-info/LICENSE
datalake-2.5.8.dist-info/METADATA
datalake-2.5.8.dist-info/WHEEL
datalake-2.5.8.dist-info/entry_points.txt
datalake-2.5.8.dist-info/top_level.txt
datalake-2.5.8.dist-info/RECORD
