Metadata-Version: 2.1
Name: datalake
Version: 2.5.8
Summary: datalake: a metadata-aware archive
Author-email: Brian Cavagnolo <brian@planet.com>
Classifier: Development Status :: 5 - Production/Stable
Classifier: Environment :: Console
Classifier: Operating System :: OS Independent
Classifier: Programming Language :: Python
Classifier: Programming Language :: Python :: 3
Requires-Python: >=3.8
License-File: LICENSE
Requires-Dist: boto3 >=1.9.68
Requires-Dist: memoized-property >=1.0.1
Requires-Dist: click >=4.1
Requires-Dist: python-dotenv >=0.1.3
Requires-Dist: requests >=2.5
Requires-Dist: six >=1.10.0
Requires-Dist: python-dateutil >=2.4.2
Requires-Dist: pytz >=2015.4
Requires-Dist: pyblake2 >=0.9.3 ; python_version < "3.6"
Provides-Extra: queuable
Requires-Dist: inotify-simple >=1.3.5 ; extra == 'queuable'
Provides-Extra: sentry
Requires-Dist: raven >=5.0.0 ; extra == 'sentry'
Provides-Extra: test
Requires-Dist: pytest <8.0.0 ; extra == 'test'
Requires-Dist: pytest-cov <4,>=2.5.1 ; extra == 'test'
Requires-Dist: moto[s3] <5,>4 ; extra == 'test'
Requires-Dist: twine <4.0.0 ; extra == 'test'
Requires-Dist: pip <22.0.0,>=20.0.0 ; extra == 'test'
Requires-Dist: wheel <0.38.0 ; extra == 'test'
Requires-Dist: flake8 <4.1,>=2.5.0 ; extra == 'test'
Requires-Dist: responses <0.22.0 ; extra == 'test'
